[{"cells":[null,null,null,null,null,null,null,null,null,null,{"type":1},{"type":1},{"type":5,"countType":1,"direction":1,"number":2},{"type":1},{"type":1},null,null,{"type":2,"countType":1,"number":0},null,{"type":1},{"type":1},{"type":1},{"type":1},null,null,null,null,{"type":1},{"type":1},null,null,null,null,{"type":1},null,{"type":1},{"type":1},{"type":1},null,null,null,{"type":5,"countType":1,"direction":3,"number":3},{"type":1},{"type":1},{"type":1},null,{"type":1},null,null,null,null,{"type":1},{"type":1},null,null,null,null,{"type":1},{"type":1},{"type":1},{"type":1},null,{"type":2,"countType":1,"number":1},null,null,{"type":1},{"type":1},null,{"type":1},{"type":1},null,null,null,{"type":5,"countType":1,"direction":2,"number":3},null,null,null,null,null,null],"underlying":[null,null,null,null,null,null,null,null,null,null,{"type":2,"countType":1,"number":0,"targetIndexes":[2,11,19,18,17,9],"clueIndexes":[17,11,19]},{"type":2,"countType":1,"number":0,"targetIndexes":[3,4,12,19,10,2],"clueIndexes":[10,19]},{"type":5,"countType":1,"direction":1,"number":2,"targetIndexes":[20,28,36,44,52,60,68,76]},{"type":2,"countType":1,"number":1,"targetIndexes":[5,6,14,21,12,4],"clueIndexes":[14]},{"type":2,"countType":1,"number":1,"targetIndexes":[6,15,23,22,21,13],"clueIndexes":[22,13]},null,null,{"type":2,"countType":1,"number":0,"targetIndexes":[9,10,18,25,16,8],"clueIndexes":[10,73]},null,{"type":2,"countType":1,"number":0,"targetIndexes":[11,12,20,27,18,10],"clueIndexes":[10,11,20,27]},{"type":2,"countType":1,"number":2,"targetIndexes":[12,21,29,28,27,19],"clueIndexes":[19,27,12]},{"type":3,"clueIndexes":[20,22,14,13]},{"type":2,"countType":1,"number":1,"targetIndexes":[14,23,31,30,29,21],"clueIndexes":[14]},null,null,null,null,{"type":2,"countType":1,"number":2,"targetIndexes":[19,20,28,35,26,18],"clueIndexes":[19,20]},{"type":3,"clueIndexes":[20,27,37,36,12]},null,null,null,null,{"type":3,"clueIndexes":[73]},null,{"type":3,"clueIndexes":[27,36]},{"type":2,"countType":2,"number":3,"targetIndexes":[28,37,45,44,43,35],"clueIndexes":[37,44,12]},{"type":2,"countType":1,"number":1,"targetIndexes":[29,30,38,45,36,28],"clueIndexes":[36]},null,null,null,{"type":5,"countType":1,"direction":3,"number":3,"targetIndexes":[42,51,52,61,62,71]},{"type":3,"clueIndexes":[41]},{"type":3,"clueIndexes":[36,44]},{"type":2,"countType":1,"number":3,"targetIndexes":[36,45,53,52,51,43],"clueIndexes":[36,12]},null,{"type":2,"countType":1,"number":0,"targetIndexes":[38,47,55,54,53,45],"clueIndexes":[64]},null,null,null,null,{"type":3,"clueIndexes":[41,44,59]},{"type":3,"clueIndexes":[41,44,12,60,59,64]},null,null,null,null,{"type":3,"clueIndexes":[73]},{"type":3,"clueIndexes":[66,59,64]},{"type":2,"countType":1,"number":3,"targetIndexes":[51,52,60,67,58,50],"clueIndexes":[60,64]},{"type":2,"countType":1,"number":2,"targetIndexes":[52,61,69,68,67,59],"clueIndexes":[12,68,59]},null,{"type":2,"countType":1,"number":1,"targetIndexes":[54,63,71,70,69,61],"clueIndexes":[41]},null,null,{"type":3,"clueIndexes":[66,73,64]},{"type":2,"countType":1,"number":2,"targetIndexes":[58,67,75,74,73,65],"clueIndexes":[]},null,{"type":2,"countType":1,"number":1,"targetIndexes":[60,69,77,76,75,67],"clueIndexes":[12,60]},{"type":3,"clueIndexes":[62,60,68]},null,null,null,{"type":5,"countType":1,"direction":2,"number":3,"targetIndexes":[65,57,49,41,33,25,17,9,1]},null,null,null,null,null,null],"columns":8,"hints":[52,33,10,69,42,57,51,65,11,19,27,20,28,35,21,44,36,68,60,59,43,37,58,14,46,66,22,13]},{"cells":[null,null,null,null,null,{"type":5,"countType":1,"direction":1,"number":5},null,null,null,{"type":2,"countType":1,"number":1},{"type":1},null,{"type":2,"countType":1,"number":3},{"type":1},{"type":1},null,null,null,{"type":5,"countType":1,"direction":1,"number":3},{"type":1},{"type":1},null,null,null,null,null,{"type":1},{"type":1},{"type":5,"countType":1,"direction":1,"number":3},{"type":1},null,null,null,{"type":1},null,{"type":1},{"type":1},null,{"type":1},null,null,{"type":2,"countType":1,"number":3},{"type":1},{"type":1},{"type":1},{"type":1},{"type":1},null,null,{"type":1},null,{"type":1},{"type":2,"countType":1,"number":4},null,{"type":1},null,null,null,{"type":1},null,{"type":1},{"type":1},null,null,null,null,null,{"type":1},{"type":1},null,null,null,null,{"type":1},{"type":1},{"type":2,"countType":1,"number":3},null,{"type":1},{"type":1},null,null,null,null,null,null,null,{"type":5,"countType":1,"direction":2,"number":5},null],"underlying":[null,null,null,null,null,{"type":5,"countType":1,"direction":1,"number":5,"targetIndexes":[13,21,29,37,45,53,61,69,77,85]},null,null,null,{"type":2,"countType":1,"number":1,"targetIndexes":[1,2,10,17,8,0],"clueIndexes":[]},{"type":3,"clueIndexes":[9]},null,{"type":2,"countType":1,"number":3,"targetIndexes":[4,13,21,20,19,11],"clueIndexes":[]},{"type":3,"clueIndexes":[12,5]},{"type":3,"clueIndexes":[86]},null,null,null,{"type":5,"countType":1,"direction":1,"number":3,"targetIndexes":[26,34,42,50,58,66,74,82]},{"type":3,"clueIndexes":[27,12]},{"type":3,"clueIndexes":[27,12]},null,null,null,null,null,{"type":3,"clueIndexes":[27,18]},{"type":2,"countType":1,"number":4,"targetIndexes":[19,20,28,35,26,18],"clueIndexes":[]},{"type":5,"countType":1,"direction":1,"number":3,"targetIndexes":[36,44,52,60,68,76,84]},{"type":3,"clueIndexes":[5]},null,null,null,{"type":3,"clueIndexes":[41]},null,{"type":3,"clueIndexes":[27,36]},{"type":2,"countType":1,"number":4,"targetIndexes":[28,37,45,44,43,35],"clueIndexes":[28]},null,{"type":3,"clueIndexes":[50,86]},null,null,{"type":2,"countType":1,"number":3,"targetIndexes":[33,34,42,49,40,32],"clueIndexes":[]},{"type":3,"clueIndexes":[18,41]},{"type":3,"clueIndexes":[36]},{"type":3,"clueIndexes":[50,52,28,36]},{"type":3,"clueIndexes":[50,5,36]},{"type":3,"clueIndexes":[86]},null,null,{"type":3,"clueIndexes":[41]},null,{"type":3,"clueIndexes":[50,52]},{"type":2,"countType":1,"number":4,"targetIndexes":[44,53,61,60,59,51],"clueIndexes":[28]},null,{"type":3,"clueIndexes":[86,72]},null,null,null,{"type":2,"countType":1,"number":1,"targetIndexes":[50,59,67,66,65,57],"clueIndexes":[18,57]},null,{"type":3,"clueIndexes":[52,72,28]},{"type":3,"clueIndexes":[52,72,5]},null,null,null,null,null,{"type":3,"clueIndexes":[58,57,72,75]},{"type":3,"clueIndexes":[57,28,75]},null,null,null,null,{"type":2,"countType":1,"number":1,"targetIndexes":[65,66,74,81,72,64],"clueIndexes":[72]},{"type":3,"clueIndexes":[18,73,75]},{"type":2,"countType":1,"number":3,"targetIndexes":[67,68,76,83,74,66],"clueIndexes":[]},null,{"type":3,"clueIndexes":[57,5]},{"type":3,"clueIndexes":[57,86]},null,null,null,null,null,null,null,{"type":5,"countType":1,"direction":2,"number":5,"targetIndexes":[78,70,62,54,46,38,30,22,14,6]},null],"columns":8,"hints":[13,61,19,77,44,46,14,54,10,45,67,68,49,60,29,33,51,74,20,42,38,78,36,35,43,73,27,26,58]}]